CubicBezier/__init__.py
CubicBezier/cubicbezier.py
CubicBezier-0.1.0.dist-info/METADATA
CubicBezier-0.1.0.dist-info/WHEEL
CubicBezier-0.1.0.dist-info/top_level.txt
CubicBezier-0.1.0.dist-info/RECORD
