Metadata-Version: 2.1
Name: CubicBezier
Version: 0.1.0
Summary: Cubic Bezier curve library
Home-page: UNKNOWN
Author: Mathias Ooi
Author-email: mathias.ho.ooi@gmail.com
License: MIT
Platform: UNKNOWN
Requires-Dist: matplotlib
Requires-Dist: numpy
